{
	"info": {
		"_postman_id": "98493ec4-ce84-48f3-a662-b2b12b3b348c",
		"name": "GlobalInvOperativa",
		"schema": "https://schema.getpostman.com/json/collection/v2.1.0/collection.json",
		"_exporter_id": "30258870"
	},
	"item": [
		{
			"name": "Articulos",
			"item": [
				{
					"name": "Get All",
					"request": {
						"method": "GET",
						"header": [],
						"url": {
							"raw": "http://localhost:8080/api/articulos",
							"protocol": "http",
							"host": [
								"localhost"
							],
							"port": "8080",
							"path": [
								"api",
								"articulos"
							]
						}
					},
					"response": []
				},
				{
					"name": "Get One",
					"request": {
						"method": "GET",
						"header": [],
						"url": {
							"raw": "http://localhost:8080/api/articulos/1",
							"protocol": "http",
							"host": [
								"localhost"
							],
							"port": "8080",
							"path": [
								"api",
								"articulos",
								"1"
							]
						}
					},
					"response": []
				},
				{
					"name": "Create",
					"request": {
						"method": "POST",
						"header": [],
						"body": {
							"mode": "raw",
							"raw": "{   \r\n    \"id\": 2,\r\n        \"nombreArticulo\": null,\r\n        \"detalle\": \"Pizza\",\r\n        \"fechaAlta\": null,\r\n        \"fechaBaja\": null,\r\n        \"loteOptimo\": 0,\r\n        \"puntoPedido\": 0,\r\n        \"stockSeguridad\": 0,\r\n        \"precioVenta\": 0.0,\r\n        \"periodo\": null,\r\n        \"modelo\": null,\r\n        \"proveedorPredeterminado\": null,\r\n        \"cgi\": 0.0,\r\n        \"cantActual\": 0\r\n    \r\n}",
							"options": {
								"raw": {
									"language": "json"
								}
							}
						},
						"url": {
							"raw": "http://localhost:8080/api/articulos",
							"protocol": "http",
							"host": [
								"localhost"
							],
							"port": "8080",
							"path": [
								"api",
								"articulos"
							]
						}
					},
					"response": []
				},
				{
					"name": "Update",
					"request": {
						"method": "PUT",
						"header": [],
						"body": {
							"mode": "raw",
							"raw": "{\r\n    \"id\": 1,\r\n    \"nombreArticulo\": \"hamburguesa\",\r\n    \"detalle\": \"queso,tomate\",\r\n    \"fechaAlta\": \"2021-10-12T00:00:00.000+00:00\",\r\n    \"fechaBaja\": null,\r\n    \"loteOptimo\": 0,\r\n    \"puntoPedido\": 0,\r\n    \"stockSeguridad\": 0,\r\n    \"modelo\": null,\r\n    \"proveedorPredeterminado\": null,\r\n    \"cantActual\": 12,\r\n    \"cgi\": 0.0\r\n}",
							"options": {
								"raw": {
									"language": "json"
								}
							}
						},
						"url": {
							"raw": "http://localhost:8080/api/articulos",
							"protocol": "http",
							"host": [
								"localhost"
							],
							"port": "8080",
							"path": [
								"api",
								"articulos"
							]
						}
					},
					"response": []
				},
				{
					"name": "Delete",
					"request": {
						"method": "DELETE",
						"header": [],
						"url": {
							"raw": "http://localhost:8080/api/articulos/1",
							"protocol": "http",
							"host": [
								"localhost"
							],
							"port": "8080",
							"path": [
								"api",
								"articulos",
								"1"
							]
						}
					},
					"response": []
				}
			]
		},
		{
			"name": "Ventas",
			"item": [
				{
					"name": "Get All",
					"request": {
						"method": "GET",
						"header": [],
						"url": {
							"raw": "http://localhost:8080/api/ventas",
							"protocol": "http",
							"host": [
								"localhost"
							],
							"port": "8080",
							"path": [
								"api",
								"ventas"
							]
						}
					},
					"response": []
				},
				{
					"name": "Get One",
					"request": {
						"method": "GET",
						"header": [],
						"url": {
							"raw": "http://localhost:8080/api/ventas/1",
							"protocol": "http",
							"host": [
								"localhost"
							],
							"port": "8080",
							"path": [
								"api",
								"ventas",
								"1"
							]
						}
					},
					"response": []
				},
				{
					"name": "Create",
					"request": {
						"method": "POST",
						"header": [],
						"body": {
							"mode": "raw",
							"raw": "{\r\n    \"fechaRealizacion\": \"2021-10-12T00:00:00\",\r\n    \"total\": 0\r\n}",
							"options": {
								"raw": {
									"language": "json"
								}
							}
						},
						"url": {
							"raw": "http://localhost:8080/api/ventas",
							"protocol": "http",
							"host": [
								"localhost"
							],
							"port": "8080",
							"path": [
								"api",
								"ventas"
							]
						}
					},
					"response": []
				},
				{
					"name": "Update",
					"request": {
						"method": "PUT",
						"header": [],
						"body": {
							"mode": "raw",
							"raw": "{\r\n    \"id\": 1,\r\n    \"fechaRealizacion\": \"2021-10-12T00:00:00.000+00:00\",\r\n    \"total\": 0.0,\r\n    \"cliente\": null,\r\n    \"detallesVenta\": []\r\n    \r\n\r\n}",
							"options": {
								"raw": {
									"language": "json"
								}
							}
						},
						"url": {
							"raw": "http://localhost:8080/api/ventas",
							"protocol": "http",
							"host": [
								"localhost"
							],
							"port": "8080",
							"path": [
								"api",
								"ventas"
							]
						}
					},
					"response": []
				},
				{
					"name": "Delete",
					"request": {
						"method": "DELETE",
						"header": [],
						"url": {
							"raw": "http://localhost:8080/api/ventas/1",
							"protocol": "http",
							"host": [
								"localhost"
							],
							"port": "8080",
							"path": [
								"api",
								"ventas",
								"1"
							]
						}
					},
					"response": []
				},
				{
					"name": "AgregarDetalleVenta",
					"request": {
						"method": "POST",
						"header": [
							{
								"key": "Content-Type",
								"value": "application/json"
							}
						],
						"body": {
							"mode": "raw",
							"raw": "{   \"id\":1,\r\n    \"cantidad\": 6,\r\n    \"subtotal\": null,\r\n    \"linea\": 1,\r\n    \"articulo\": null\r\n}"
						},
						"url": {
							"raw": "http://localhost:8080/api/ventas/agregarDetalle/1",
							"protocol": "http",
							"host": [
								"localhost"
							],
							"port": "8080",
							"path": [
								"api",
								"ventas",
								"agregarDetalle",
								"1"
							]
						}
					},
					"response": []
				},
				{
					"name": "CalcularTotal",
					"request": {
						"method": "POST",
						"header": [],
						"url": {
							"raw": "http://localhost:8080/api/ventas/calcularTotal/1",
							"protocol": "http",
							"host": [
								"localhost"
							],
							"port": "8080",
							"path": [
								"api",
								"ventas",
								"calcularTotal",
								"1"
							]
						}
					},
					"response": []
				},
				{
					"name": "AgregarCliente",
					"request": {
						"method": "POST",
						"header": [],
						"url": {
							"raw": "http://localhost:8080/api/ventas/agregarCliente/1/1",
							"protocol": "http",
							"host": [
								"localhost"
							],
							"port": "8080",
							"path": [
								"api",
								"ventas",
								"agregarCliente",
								"1",
								"1"
							]
						}
					},
					"response": []
				}
			]
		},
		{
			"name": "DetallesVenta",
			"item": [
				{
					"name": "Get All",
					"request": {
						"method": "GET",
						"header": [],
						"url": {
							"raw": "http://localhost:8080/api/detallesVenta",
							"protocol": "http",
							"host": [
								"localhost"
							],
							"port": "8080",
							"path": [
								"api",
								"detallesVenta"
							]
						}
					},
					"response": []
				},
				{
					"name": "Get One",
					"request": {
						"method": "GET",
						"header": [],
						"url": {
							"raw": "http://localhost:8080/api/detallesVenta/1",
							"protocol": "http",
							"host": [
								"localhost"
							],
							"port": "8080",
							"path": [
								"api",
								"detallesVenta",
								"1"
							]
						}
					},
					"response": []
				},
				{
					"name": "Create",
					"request": {
						"method": "POST",
						"header": [],
						"body": {
							"mode": "raw",
							"raw": "{   \r\n    \"id\": 1,\r\n    \"cantidad\": 1,\r\n    \"subtotal\": 420,\r\n    \"linea\": 2\r\n}",
							"options": {
								"raw": {
									"language": "json"
								}
							}
						},
						"url": {
							"raw": "http://localhost:8080/api/detallesVenta",
							"protocol": "http",
							"host": [
								"localhost"
							],
							"port": "8080",
							"path": [
								"api",
								"detallesVenta"
							]
						}
					},
					"response": []
				},
				{
					"name": "Update",
					"request": {
						"method": "PUT",
						"header": [],
						"body": {
							"mode": "raw",
							"raw": "\r\n    {   \"id\":3,\r\n    \"cantidad\": 6,\r\n    \"subtotal\": null,\r\n    \"linea\": 3,\r\n    \"articulo\": null\r\n}\r\n",
							"options": {
								"raw": {
									"language": "json"
								}
							}
						},
						"url": {
							"raw": "http://localhost:8080/api/detallesVenta/3",
							"protocol": "http",
							"host": [
								"localhost"
							],
							"port": "8080",
							"path": [
								"api",
								"detallesVenta",
								"3"
							]
						}
					},
					"response": []
				},
				{
					"name": "Delete",
					"request": {
						"method": "DELETE",
						"header": [],
						"url": {
							"raw": "http://localhost:8080/api/detallesVenta/2",
							"protocol": "http",
							"host": [
								"localhost"
							],
							"port": "8080",
							"path": [
								"api",
								"detallesVenta",
								"2"
							]
						}
					},
					"response": []
				},
				{
					"name": "AgregarArticulo",
					"request": {
						"method": "POST",
						"header": [],
						"url": {
							"raw": "http://localhost:8080/api/detallesVenta/agregarArticulo/3/1",
							"protocol": "http",
							"host": [
								"localhost"
							],
							"port": "8080",
							"path": [
								"api",
								"detallesVenta",
								"agregarArticulo",
								"3",
								"1"
							]
						}
					},
					"response": []
				}
			]
		},
		{
			"name": "Clientes",
			"item": [
				{
					"name": "Get All",
					"request": {
						"method": "GET",
						"header": [],
						"url": {
							"raw": "http://localhost:8080/api/clientes",
							"protocol": "http",
							"host": [
								"localhost"
							],
							"port": "8080",
							"path": [
								"api",
								"clientes"
							]
						}
					},
					"response": []
				},
				{
					"name": "Get One",
					"request": {
						"method": "GET",
						"header": [],
						"url": {
							"raw": "http://localhost:8080/api/articulos/1",
							"protocol": "http",
							"host": [
								"localhost"
							],
							"port": "8080",
							"path": [
								"api",
								"articulos",
								"1"
							]
						}
					},
					"response": []
				},
				{
					"name": "Create",
					"request": {
						"method": "POST",
						"header": [],
						"body": {
							"mode": "raw",
							"raw": "{\r\n    \"nombre\": \"Gerardo Guzmán\",\r\n    \"dni\": 12321\r\n    \r\n}",
							"options": {
								"raw": {
									"language": "json"
								}
							}
						},
						"url": {
							"raw": "http://localhost:8080/api/clientes",
							"protocol": "http",
							"host": [
								"localhost"
							],
							"port": "8080",
							"path": [
								"api",
								"clientes"
							]
						}
					},
					"response": []
				},
				{
					"name": "Update",
					"request": {
						"method": "PUT",
						"header": [],
						"body": {
							"mode": "raw",
							"raw": "{\r\n        \"id\": 4,\r\n        \"nombre\": \"Julio Guzmán\",\r\n        \"dni\": 3213242\r\n}",
							"options": {
								"raw": {
									"language": "json"
								}
							}
						},
						"url": {
							"raw": "http://localhost:8080/api/clientes/4",
							"protocol": "http",
							"host": [
								"localhost"
							],
							"port": "8080",
							"path": [
								"api",
								"clientes",
								"4"
							]
						}
					},
					"response": []
				},
				{
					"name": "Delete",
					"request": {
						"method": "DELETE",
						"header": [],
						"url": {
							"raw": "http://localhost:8080/api/clientes/2",
							"protocol": "http",
							"host": [
								"localhost"
							],
							"port": "8080",
							"path": [
								"api",
								"clientes",
								"2"
							]
						}
					},
					"response": []
				}
			]
		},
		{
			"name": "Proveedores",
			"item": [
				{
					"name": "Get All",
					"request": {
						"method": "GET",
						"header": [],
						"url": {
							"raw": "http://localhost:8080/api/proveedores",
							"protocol": "http",
							"host": [
								"localhost"
							],
							"port": "8080",
							"path": [
								"api",
								"proveedores"
							]
						}
					},
					"response": []
				},
				{
					"name": "Get One",
					"request": {
						"method": "GET",
						"header": [],
						"url": {
							"raw": "http://localhost:8080/api/proveedores/1",
							"protocol": "http",
							"host": [
								"localhost"
							],
							"port": "8080",
							"path": [
								"api",
								"proveedores",
								"1"
							]
						}
					},
					"response": []
				},
				{
					"name": "Create",
					"request": {
						"method": "POST",
						"header": [
							{
								"key": "Content-Type",
								"value": "application/json"
							}
						],
						"body": {
							"mode": "raw",
							"raw": "{   \r\n    \"nombre\":\"ale\",\r\n    \"telefono\":2613004548,\r\n    \"direccion\":\"Castelar 825\",\r\n    \"mail\":\"alear12373@gmail.com\",\r\n    \"fechaAlta\":\"2021-10-12T00:00:00\",\r\n    \"fechaBaja\":null\r\n}",
							"options": {
								"raw": {
									"language": "json"
								}
							}
						},
						"url": {
							"raw": "http://localhost:8080/api/proveedores",
							"protocol": "http",
							"host": [
								"localhost"
							],
							"port": "8080",
							"path": [
								"api",
								"proveedores"
							]
						}
					},
					"response": []
				},
				{
					"name": "Update",
					"request": {
						"method": "PUT",
						"header": [],
						"body": {
							"mode": "raw",
							"raw": "{\r\n    \"id\": 1,\r\n    \"nombreArticulo\": \"hamburguesa\",\r\n    \"detalle\": \"queso,tomate\",\r\n    \"fechaAlta\": \"2021-10-12T00:00:00.000+00:00\",\r\n    \"fechaBaja\": null,\r\n    \"loteOptimo\": 0,\r\n    \"puntoPedido\": 0,\r\n    \"stockSeguridad\": 0,\r\n    \"modelo\": null,\r\n    \"proveedorPredeterminado\": null,\r\n    \"cantActual\": 12,\r\n    \"cgi\": 0.0\r\n}",
							"options": {
								"raw": {
									"language": "json"
								}
							}
						},
						"url": {
							"raw": "http://localhost:8080/api/proveedores",
							"protocol": "http",
							"host": [
								"localhost"
							],
							"port": "8080",
							"path": [
								"api",
								"proveedores"
							]
						}
					},
					"response": []
				},
				{
					"name": "Delete",
					"request": {
						"method": "DELETE",
						"header": [],
						"url": {
							"raw": "http://localhost:8080/api/proveedores/1",
							"protocol": "http",
							"host": [
								"localhost"
							],
							"port": "8080",
							"path": [
								"api",
								"proveedores",
								"1"
							]
						}
					},
					"response": []
				}
			]
		},
		{
			"name": "ProveedorArticulos",
			"item": [
				{
					"name": "Get All",
					"request": {
						"method": "GET",
						"header": [],
						"url": {
							"raw": "http://localhost:8080/api/proveedores",
							"protocol": "http",
							"host": [
								"localhost"
							],
							"port": "8080",
							"path": [
								"api",
								"proveedores"
							]
						}
					},
					"response": []
				},
				{
					"name": "Get One",
					"request": {
						"method": "GET",
						"header": [],
						"url": {
							"raw": "http://localhost:8080/api/proveedores/1",
							"protocol": "http",
							"host": [
								"localhost"
							],
							"port": "8080",
							"path": [
								"api",
								"proveedores",
								"1"
							]
						}
					},
					"response": []
				},
				{
					"name": "Create",
					"request": {
						"method": "POST",
						"header": [
							{
								"key": "Content-Type",
								"value": "application/json"
							}
						],
						"body": {
							"mode": "raw",
							"raw": "{\r\n    \"fechaHoraBaja\":\"2021-10-12T00:00:00.000+00:00\",\r\n    \"fechaHoraAlta\":null,\r\n    \"tiempoPedido\":2,\r\n    \"costoPedido\":2.3,\r\n    \"costoAlmacenamiento\":null,\r\n    \"costoProducto\":33.2,\r\n    \"proveedor\":{\r\n    \"id\": 3,\r\n    \"nombre\": \"ale\",\r\n    \"telefono\": 2.613004548E9,\r\n    \"direccion\": \"Castelar 825\",\r\n    \"mail\": \"alear12373@gmail.com\",\r\n    \"fechaAlta\": \"2021-10-12T00:00:00.000+00:00\",\r\n    \"fechaBaja\": null\r\n},\r\n    \"articulo\":{\r\n    \"id\": 1,\r\n    \"nombreArticulo\": \"hamburguesa\",\r\n    \"detalle\": \"queso,tomate\",\r\n    \"fechaAlta\": \"2021-10-12T00:00:00.000+00:00\",\r\n    \"fechaBaja\": null,\r\n    \"loteOptimo\": 0,\r\n    \"puntoPedido\": 0,\r\n    \"stockSeguridad\": 0,\r\n    \"modelo\": \"MODELO_LOTE_FIJO\",\r\n    \"proveedorPredeterminado\": null,\r\n    \"cantActual\": 12,\r\n    \"cgi\": 0.0\r\n}\r\n}",
							"options": {
								"raw": {
									"language": "json"
								}
							}
						},
						"url": {
							"raw": "http://localhost:8080/api/proveedorArticulos",
							"protocol": "http",
							"host": [
								"localhost"
							],
							"port": "8080",
							"path": [
								"api",
								"proveedorArticulos"
							]
						}
					},
					"response": []
				},
				{
					"name": "Update",
					"request": {
						"method": "PUT",
						"header": [],
						"body": {
							"mode": "raw",
							"raw": "{\r\n    \"id\": 1,\r\n    \"nombreArticulo\": \"hamburguesa\",\r\n    \"detalle\": \"queso,tomate\",\r\n    \"fechaAlta\": \"2021-10-12T00:00:00.000+00:00\",\r\n    \"fechaBaja\": null,\r\n    \"loteOptimo\": 0,\r\n    \"puntoPedido\": 0,\r\n    \"stockSeguridad\": 0,\r\n    \"modelo\": null,\r\n    \"proveedorPredeterminado\": null,\r\n    \"cantActual\": 12,\r\n    \"cgi\": 0.0\r\n}",
							"options": {
								"raw": {
									"language": "json"
								}
							}
						},
						"url": {
							"raw": "http://localhost:8080/api/proveedores",
							"protocol": "http",
							"host": [
								"localhost"
							],
							"port": "8080",
							"path": [
								"api",
								"proveedores"
							]
						}
					},
					"response": []
				},
				{
					"name": "Delete",
					"request": {
						"method": "DELETE",
						"header": [],
						"url": {
							"raw": "http://localhost:8080/api/proveedores/1",
							"protocol": "http",
							"host": [
								"localhost"
							],
							"port": "8080",
							"path": [
								"api",
								"proveedores",
								"1"
							]
						}
					},
					"response": []
				}
			]
		},
		{
			"name": "Demanda",
			"item": [
				{
					"name": "Get All",
					"request": {
						"method": "GET",
						"header": [],
						"url": {
							"raw": "http://localhost:8080/api/demandas",
							"protocol": "http",
							"host": [
								"localhost"
							],
							"port": "8080",
							"path": [
								"api",
								"demandas"
							]
						}
					},
					"response": []
				},
				{
					"name": "Get One",
					"request": {
						"method": "GET",
						"header": [],
						"url": {
							"raw": "http://localhost:8080/api/demandas/37",
							"protocol": "http",
							"host": [
								"localhost"
							],
							"port": "8080",
							"path": [
								"api",
								"demandas",
								"37"
							]
						}
					},
					"response": []
				},
				{
					"name": "Create",
					"request": {
						"method": "POST",
						"header": [
							{
								"key": "Content-Type",
								"value": "application/json"
							}
						],
						"body": {
							"mode": "raw",
							"raw": "    \r\n    {\r\n        \r\n        \"numPeriodo\": 1,\r\n        \"anio\": 2024,\r\n        \"cantTotalDemanda\": 100,\r\n        \"articulo\": {\r\n            \"id\": 1,\r\n            \"nombreArticulo\": null,\r\n            \"detalle\": \"Hamburguesa\",\r\n            \"fechaAlta\": null,\r\n            \"fechaBaja\": null,\r\n            \"loteOptimo\": 0,\r\n            \"puntoPedido\": 0,\r\n            \"stockSeguridad\": 0,\r\n            \"precioVenta\": 0.0,\r\n            \"periodo\": null,\r\n            \"modelo\": null,\r\n            \"proveedorPredeterminado\": null,\r\n            \"cgi\": 0.0,\r\n            \"cantActual\": 0\r\n        },\r\n        \"detallesVenta\": []\r\n    }",
							"options": {
								"raw": {
									"language": "json"
								}
							}
						},
						"url": {
							"raw": "http://localhost:8080/api/demandas",
							"protocol": "http",
							"host": [
								"localhost"
							],
							"port": "8080",
							"path": [
								"api",
								"demandas"
							]
						}
					},
					"response": []
				},
				{
					"name": "Update",
					"request": {
						"method": "PUT",
						"header": [],
						"body": {
							"mode": "raw",
							"raw": "{\r\n    \"id\": 1,\r\n    \"nombreArticulo\": \"hamburguesa\",\r\n    \"detalle\": \"queso,tomate\",\r\n    \"fechaAlta\": \"2021-10-12T00:00:00.000+00:00\",\r\n    \"fechaBaja\": null,\r\n    \"loteOptimo\": 0,\r\n    \"puntoPedido\": 0,\r\n    \"stockSeguridad\": 0,\r\n    \"modelo\": null,\r\n    \"proveedorPredeterminado\": null,\r\n    \"cantActual\": 12,\r\n    \"cgi\": 0.0\r\n}",
							"options": {
								"raw": {
									"language": "json"
								}
							}
						},
						"url": {
							"raw": "http://localhost:8080/api/demandas",
							"protocol": "http",
							"host": [
								"localhost"
							],
							"port": "8080",
							"path": [
								"api",
								"demandas"
							]
						}
					},
					"response": []
				},
				{
					"name": "Delete",
					"request": {
						"method": "DELETE",
						"header": [],
						"url": {
							"raw": "http://localhost:8080/api/demandas/1",
							"protocol": "http",
							"host": [
								"localhost"
							],
							"port": "8080",
							"path": [
								"api",
								"demandas",
								"1"
							]
						}
					},
					"response": []
				},
				{
					"name": "SetArticulo",
					"request": {
						"method": "POST",
						"header": [],
						"url": {
							"raw": "http://localhost:8080/api/demandas/setearArticulo/1/1",
							"protocol": "http",
							"host": [
								"localhost"
							],
							"port": "8080",
							"path": [
								"api",
								"demandas",
								"setearArticulo",
								"1",
								"1"
							]
						}
					},
					"response": []
				},
				{
					"name": "SetDetallesVenta",
					"request": {
						"method": "POST",
						"header": [],
						"url": {
							"raw": "http://localhost:8080/api/demandas/setearDetallesVenta/37",
							"protocol": "http",
							"host": [
								"localhost"
							],
							"port": "8080",
							"path": [
								"api",
								"demandas",
								"setearDetallesVenta",
								"37"
							]
						}
					},
					"response": []
				},
				{
					"name": "SetTotalDemandada",
					"request": {
						"method": "POST",
						"header": [],
						"url": {
							"raw": "http://localhost:8080/api/demandas/setearTotalDemanda/1",
							"protocol": "http",
							"host": [
								"localhost"
							],
							"port": "8080",
							"path": [
								"api",
								"demandas",
								"setearTotalDemanda",
								"1"
							]
						}
					},
					"response": []
				}
			]
		},
		{
			"name": "Demanda Pronosticada",
			"item": [
				{
					"name": "Get All",
					"request": {
						"method": "GET",
						"header": [],
						"url": {
							"raw": "http://localhost:8080/api/demandaspronosticada",
							"protocol": "http",
							"host": [
								"localhost"
							],
							"port": "8080",
							"path": [
								"api",
								"demandaspronosticada"
							]
						}
					},
					"response": []
				},
				{
					"name": "Get One",
					"request": {
						"method": "GET",
						"header": [],
						"url": {
							"raw": "http://localhost:8080/api/demandapronosticada/1",
							"protocol": "http",
							"host": [
								"localhost"
							],
							"port": "8080",
							"path": [
								"api",
								"demandapronosticada",
								"1"
							]
						}
					},
					"response": []
				},
				{
					"name": "Create",
					"request": {
						"method": "POST",
						"header": [
							{
								"key": "Content-Type",
								"value": "application/json"
							}
						],
						"body": {
							"mode": "raw",
							"raw": "{\r\n        \"id\": 40,\r\n        \"cantidadDemandadaPronostico\": 81.83333333333333,\r\n        \"valorErrorPronosticoDemandaPronosticada\": 0.0,\r\n        \"nroPeriodoDemandaPronosticada\": 1,\r\n        \"anioDemandaPronosticada\": 2024,\r\n        \"cantidadDemandaReal\": 0,\r\n        \"demandaRealAsociada\": null\r\n    }",
							"options": {
								"raw": {
									"language": "json"
								}
							}
						},
						"url": {
							"raw": "http://localhost:8080/api/demandaspronosticada",
							"protocol": "http",
							"host": [
								"localhost"
							],
							"port": "8080",
							"path": [
								"api",
								"demandaspronosticada"
							]
						}
					},
					"response": []
				},
				{
					"name": "Update",
					"request": {
						"method": "PUT",
						"header": [],
						"body": {
							"mode": "raw",
							"raw": "{\r\n        \"id\": 1,\r\n        \"cantidadDemandadaPronostico\": 81.83333333333333,\r\n        \"valorErrorPronosticoDemandaPronosticada\": 0.0,\r\n        \"nroPeriodoDemandaPronosticada\": 1,\r\n        \"anioDemandaPronosticada\": 2024,\r\n        \"cantidadDemandaReal\": 0,\r\n        \"demandaRealAsociada\": null\r\n    }",
							"options": {
								"raw": {
									"language": "json"
								}
							}
						},
						"url": {
							"raw": "http://localhost:8080/api/demandapronosticada",
							"protocol": "http",
							"host": [
								"localhost"
							],
							"port": "8080",
							"path": [
								"api",
								"demandapronosticada"
							]
						}
					},
					"response": []
				},
				{
					"name": "Delete",
					"request": {
						"method": "DELETE",
						"header": [],
						"url": {
							"raw": "http://localhost:8080/api/demandaspronosticada/2",
							"protocol": "http",
							"host": [
								"localhost"
							],
							"port": "8080",
							"path": [
								"api",
								"demandaspronosticada",
								"2"
							]
						}
					},
					"response": []
				},
				{
					"name": "Asignar Demanda",
					"request": {
						"method": "POST",
						"header": [],
						"url": {
							"raw": "http://localhost:8080/api/demandaspronosticada/asignarDemanda/1/37",
							"protocol": "http",
							"host": [
								"localhost"
							],
							"port": "8080",
							"path": [
								"api",
								"demandaspronosticada",
								"asignarDemanda",
								"1",
								"37"
							]
						}
					},
					"response": []
				}
			]
		},
		{
			"name": "Pronostico",
			"item": [
				{
					"name": "Get All",
					"protocolProfileBehavior": {
						"disableBodyPruning": true
					},
					"request": {
						"method": "GET",
						"header": [],
						"body": {
							"mode": "raw",
							"raw": "",
							"options": {
								"raw": {
									"language": "json"
								}
							}
						},
						"url": {
							"raw": "http://localhost:8080/api/pronosticos",
							"protocol": "http",
							"host": [
								"localhost"
							],
							"port": "8080",
							"path": [
								"api",
								"pronosticos"
							]
						}
					},
					"response": []
				},
				{
					"name": "Get One",
					"request": {
						"method": "GET",
						"header": [],
						"url": {
							"raw": "http://localhost:8080/api/pronosticos/1",
							"protocol": "http",
							"host": [
								"localhost"
							],
							"port": "8080",
							"path": [
								"api",
								"pronosticos",
								"1"
							]
						}
					},
					"response": []
				},
				{
					"name": "Create",
					"request": {
						"method": "POST",
						"header": [
							{
								"key": "Content-Type",
								"value": "application/json"
							}
						],
						"body": {
							"mode": "raw",
							"raw": "{\r\n        \"id\": 2,\r\n        \"nombrePronostico\": \"Promedio_Ponderado\",\r\n        \"errorAceptable\": 0.0,\r\n        \"cantidadPeriodosHistoricos\": 3,\r\n        \"demandaPronosticada\": null,\r\n        \"articulo\": {\r\n            \"id\": 1,\r\n            \"nombreArticulo\": null,\r\n            \"detalle\": \"Hamburguesa\",\r\n            \"fechaAlta\": null,\r\n            \"fechaBaja\": null,\r\n            \"loteOptimo\": 0,\r\n            \"puntoPedido\": 0,\r\n            \"stockSeguridad\": 0,\r\n            \"precioVenta\": 0.0,\r\n            \"periodo\": null,\r\n            \"modelo\": null,\r\n            \"proveedorPredeterminado\": null,\r\n            \"cgi\": 0.0,\r\n            \"cantActual\": 0\r\n        }\r\n    }",
							"options": {
								"raw": {
									"language": "json"
								}
							}
						},
						"url": {
							"raw": "http://localhost:8080/api/pronosticos",
							"protocol": "http",
							"host": [
								"localhost"
							],
							"port": "8080",
							"path": [
								"api",
								"pronosticos"
							]
						}
					},
					"response": []
				},
				{
					"name": "Update",
					"request": {
						"method": "PUT",
						"header": [],
						"body": {
							"mode": "raw",
							"raw": "",
							"options": {
								"raw": {
									"language": "json"
								}
							}
						},
						"url": {
							"raw": "http://localhost:8080/api/pronosticos",
							"protocol": "http",
							"host": [
								"localhost"
							],
							"port": "8080",
							"path": [
								"api",
								"pronosticos"
							]
						}
					},
					"response": []
				},
				{
					"name": "Delete",
					"request": {
						"method": "DELETE",
						"header": [],
						"url": {
							"raw": "http://localhost:8080/api/pronosticos/1",
							"protocol": "http",
							"host": [
								"localhost"
							],
							"port": "8080",
							"path": [
								"api",
								"pronosticos",
								"1"
							]
						}
					},
					"response": []
				},
				{
					"name": "SetArticulo",
					"request": {
						"method": "POST",
						"header": [],
						"url": {
							"raw": "http://localhost:8080/api/pronosticos/asignarArticulo/5/1",
							"protocol": "http",
							"host": [
								"localhost"
							],
							"port": "8080",
							"path": [
								"api",
								"pronosticos",
								"asignarArticulo",
								"5",
								"1"
							]
						}
					},
					"response": []
				},
				{
					"name": "Generar OrdenCompra",
					"request": {
						"method": "POST",
						"header": [],
						"url": {
							"raw": "http://localhost:8080/api/pronosticos/generarOrdenCompra/1",
							"protocol": "http",
							"host": [
								"localhost"
							],
							"port": "8080",
							"path": [
								"api",
								"pronosticos",
								"generarOrdenCompra",
								"1"
							]
						}
					},
					"response": []
				},
				{
					"name": "PromedioPonderado",
					"request": {
						"method": "POST",
						"header": [],
						"url": {
							"raw": "http://localhost:8080/api/pronosticos/calcularPromedioPonderado/1/2023",
							"protocol": "http",
							"host": [
								"localhost"
							],
							"port": "8080",
							"path": [
								"api",
								"pronosticos",
								"calcularPromedioPonderado",
								"1",
								"2023"
							]
						}
					},
					"response": []
				},
				{
					"name": "PromedioSuavizado",
					"request": {
						"method": "POST",
						"header": [],
						"url": {
							"raw": "http://localhost:8080/api/pronosticos/calcularPMSuavizado/2/98/0.2/2023",
							"protocol": "http",
							"host": [
								"localhost"
							],
							"port": "8080",
							"path": [
								"api",
								"pronosticos",
								"calcularPMSuavizado",
								"2",
								"98",
								"0.2",
								"2023"
							]
						}
					},
					"response": []
				},
				{
					"name": "Regresion Lineal",
					"request": {
						"method": "POST",
						"header": [],
						"url": {
							"raw": "http://localhost:8080/api/pronosticos/calcularRegresionLineal/3/2024",
							"protocol": "http",
							"host": [
								"localhost"
							],
							"port": "8080",
							"path": [
								"api",
								"pronosticos",
								"calcularRegresionLineal",
								"3",
								"2024"
							]
						}
					},
					"response": []
				},
				{
					"name": "PronosticoEstacionalidad",
					"request": {
						"method": "POST",
						"header": [],
						"url": {
							"raw": "http://localhost:8080/api/pronosticos/calcularPronosticoEstacionalidad/4/2024/1250",
							"protocol": "http",
							"host": [
								"localhost"
							],
							"port": "8080",
							"path": [
								"api",
								"pronosticos",
								"calcularPronosticoEstacionalidad",
								"4",
								"2024",
								"1250"
							]
						}
					},
					"response": []
				}
			]
		}
	]
}