{
	"info": {
		"_postman_id": "27a75383-30f2-4f0e-8b04-9468e4bc6f0e",
		"name": "GlobalInvOperativa",
		"schema": "https://schema.getpostman.com/json/collection/v2.1.0/collection.json",
		"_exporter_id": "30258870"
	},
	"item": [
		{
			"name": "Articulos",
			"item": [
				{
					"name": "Get All",
					"request": {
						"method": "GET",
						"header": [],
						"url": {
							"raw": "http://localhost:8080/api/articulos",
							"protocol": "http",
							"host": [
								"localhost"
							],
							"port": "8080",
							"path": [
								"api",
								"articulos"
							]
						}
					},
					"response": []
				},
				{
					"name": "Get One",
					"request": {
						"method": "GET",
						"header": [],
						"url": {
							"raw": "http://localhost:8080/api/articulos/1",
							"protocol": "http",
							"host": [
								"localhost"
							],
							"port": "8080",
							"path": [
								"api",
								"articulos",
								"1"
							]
						}
					},
					"response": []
				},
				{
					"name": "Create",
					"request": {
						"method": "POST",
						"header": [],
						"body": {
							"mode": "raw",
							"raw": "{   \r\n    \"id\":1,\r\n    \"nombreArticulo\": \"hamburguesa\",\r\n    \"detalle\": \"queso,tomate\",\r\n    \"fechaAlta\": \"2021-10-12T00:00:00\",\r\n    \"fechaBaja\": null,\r\n    \"loteOptimo\": null,\r\n    \"puntoPedido\":null,\r\n    \"stockSeguridad\": null,\r\n    \"CGI\":null,\r\n    \"cantActual\": 12,\r\n    \"modelo\": null,\r\n    \"proveedorPredeterminado\": null\r\n    \r\n}",
							"options": {
								"raw": {
									"language": "json"
								}
							}
						},
						"url": {
							"raw": "http://localhost:8080/api/articulos",
							"protocol": "http",
							"host": [
								"localhost"
							],
							"port": "8080",
							"path": [
								"api",
								"articulos"
							]
						}
					},
					"response": []
				},
				{
					"name": "Update",
					"request": {
						"method": "PUT",
						"header": [],
						"body": {
							"mode": "raw",
							"raw": "{\r\n    \"id\": 1,\r\n    \"nombreArticulo\": \"hamburguesa\",\r\n    \"detalle\": \"queso,tomate\",\r\n    \"fechaAlta\": \"2021-10-12T00:00:00.000+00:00\",\r\n    \"fechaBaja\": null,\r\n    \"loteOptimo\": 0,\r\n    \"puntoPedido\": 0,\r\n    \"stockSeguridad\": 0,\r\n    \"modelo\": null,\r\n    \"proveedorPredeterminado\": null,\r\n    \"cantActual\": 12,\r\n    \"cgi\": 0.0\r\n}",
							"options": {
								"raw": {
									"language": "json"
								}
							}
						},
						"url": {
							"raw": "http://localhost:8080/api/articulos",
							"protocol": "http",
							"host": [
								"localhost"
							],
							"port": "8080",
							"path": [
								"api",
								"articulos"
							]
						}
					},
					"response": []
				},
				{
					"name": "Delete",
					"request": {
						"method": "DELETE",
						"header": [],
						"url": {
							"raw": "http://localhost:8080/api/articulos/1",
							"protocol": "http",
							"host": [
								"localhost"
							],
							"port": "8080",
							"path": [
								"api",
								"articulos",
								"1"
							]
						}
					},
					"response": []
				}
			]
		},
		{
			"name": "Ventas",
			"item": [
				{
					"name": "Get All",
					"request": {
						"method": "GET",
						"header": [],
						"url": {
							"raw": "http://localhost:8080/api/ventas",
							"protocol": "http",
							"host": [
								"localhost"
							],
							"port": "8080",
							"path": [
								"api",
								"ventas"
							]
						}
					},
					"response": []
				},
				{
					"name": "Get One",
					"request": {
						"method": "GET",
						"header": [],
						"url": {
							"raw": "http://localhost:8080/api/ventas/1",
							"protocol": "http",
							"host": [
								"localhost"
							],
							"port": "8080",
							"path": [
								"api",
								"ventas",
								"1"
							]
						}
					},
					"response": []
				},
				{
					"name": "Create",
					"request": {
						"method": "POST",
						"header": [],
						"body": {
							"mode": "raw",
							"raw": "{\r\n    \"fechaRealizacion\": \"2021-10-12T00:00:00\",\r\n    \"total\": 0\r\n}",
							"options": {
								"raw": {
									"language": "json"
								}
							}
						},
						"url": {
							"raw": "http://localhost:8080/api/ventas",
							"protocol": "http",
							"host": [
								"localhost"
							],
							"port": "8080",
							"path": [
								"api",
								"ventas"
							]
						}
					},
					"response": []
				},
				{
					"name": "Update",
					"request": {
						"method": "PUT",
						"header": [],
						"body": {
							"mode": "raw",
							"raw": "{\r\n    \"id\": 1,\r\n    \"fechaRealizacion\": \"2021-10-12T00:00:00.000+00:00\",\r\n    \"total\": 0.0,\r\n    \"cliente\": null,\r\n    \"detallesVenta\": []\r\n    \r\n\r\n}",
							"options": {
								"raw": {
									"language": "json"
								}
							}
						},
						"url": {
							"raw": "http://localhost:8080/api/ventas",
							"protocol": "http",
							"host": [
								"localhost"
							],
							"port": "8080",
							"path": [
								"api",
								"ventas"
							]
						}
					},
					"response": []
				},
				{
					"name": "Delete",
					"request": {
						"method": "DELETE",
						"header": [],
						"url": {
							"raw": "http://localhost:8080/api/ventas/1",
							"protocol": "http",
							"host": [
								"localhost"
							],
							"port": "8080",
							"path": [
								"api",
								"ventas",
								"1"
							]
						}
					},
					"response": []
				},
				{
					"name": "AgregarDetalleVenta",
					"request": {
						"method": "POST",
						"header": [
							{
								"key": "Content-Type",
								"value": "application/json",
								"type": "text"
							}
						],
						"body": {
							"mode": "raw",
							"raw": "{   \"id\":1,\r\n    \"cantidad\": 2,\r\n    \"subtotal\": 320.0,\r\n    \"linea\": 1,\r\n    \"articulo\": null\r\n}"
						},
						"url": {
							"raw": "http://localhost:8080/api/ventas/agregarDetalle/1",
							"protocol": "http",
							"host": [
								"localhost"
							],
							"port": "8080",
							"path": [
								"api",
								"ventas",
								"agregarDetalle",
								"1"
							]
						}
					},
					"response": []
				}
			]
		},
		{
			"name": "DetallesVenta",
			"item": [
				{
					"name": "Get All",
					"request": {
						"method": "GET",
						"header": [],
						"url": {
							"raw": "http://localhost:8080/api/detallesVenta",
							"protocol": "http",
							"host": [
								"localhost"
							],
							"port": "8080",
							"path": [
								"api",
								"detallesVenta"
							]
						}
					},
					"response": []
				},
				{
					"name": "Get One",
					"request": {
						"method": "GET",
						"header": [],
						"url": {
							"raw": "http://localhost:8080/api/detallesVenta/1",
							"protocol": "http",
							"host": [
								"localhost"
							],
							"port": "8080",
							"path": [
								"api",
								"detallesVenta",
								"1"
							]
						}
					},
					"response": []
				},
				{
					"name": "Create",
					"request": {
						"method": "POST",
						"header": [],
						"body": {
							"mode": "raw",
							"raw": "{   \r\n    \"id\": 1,\r\n    \"cantidad\": 1,\r\n    \"subtotal\": 420,\r\n    \"linea\": 2\r\n}",
							"options": {
								"raw": {
									"language": "json"
								}
							}
						},
						"url": {
							"raw": "http://localhost:8080/api/detallesVenta",
							"protocol": "http",
							"host": [
								"localhost"
							],
							"port": "8080",
							"path": [
								"api",
								"detallesVenta"
							]
						}
					},
					"response": []
				},
				{
					"name": "Update",
					"request": {
						"method": "PUT",
						"header": [],
						"body": {
							"mode": "raw",
							"raw": "{\r\n    \"id\": 2,\r\n    \"cantidad\": 1,\r\n    \"subtotal\": 420.0,\r\n    \"linea\": 2,\r\n    \"articulo\": null\r\n}",
							"options": {
								"raw": {
									"language": "json"
								}
							}
						},
						"url": {
							"raw": "http://localhost:8080/api/detallesVenta/3",
							"protocol": "http",
							"host": [
								"localhost"
							],
							"port": "8080",
							"path": [
								"api",
								"detallesVenta",
								"3"
							]
						}
					},
					"response": []
				},
				{
					"name": "Delete",
					"request": {
						"method": "DELETE",
						"header": [],
						"url": {
							"raw": "http://localhost:8080/api/detallesVenta/2",
							"protocol": "http",
							"host": [
								"localhost"
							],
							"port": "8080",
							"path": [
								"api",
								"detallesVenta",
								"2"
							]
						}
					},
					"response": []
				},
				{
					"name": "AgregarArticulo",
					"request": {
						"method": "POST",
						"header": [],
						"body": {
							"mode": "raw",
							"raw": "{       \"id\":1,\r\n        \"nombreArticulo\": \"hamburguesa\",\r\n        \"detalle\": \"queso,tomate\",\r\n        \"fechaAlta\": \"2021-10-12T00:00:00.000+00:00\",\r\n        \"fechaBaja\": null,\r\n        \"loteOptimo\": 0,\r\n        \"puntoPedido\": 0,\r\n        \"stockSeguridad\": 0,\r\n        \"modelo\": null,\r\n        \"proveedorPredeterminado\": null,\r\n        \"cantActual\": 12,\r\n        \"cgi\": 0.0\r\n    }",
							"options": {
								"raw": {
									"language": "json"
								}
							}
						},
						"url": {
							"raw": "http://localhost:8080/api/detallesVenta/agregarArticulo/1",
							"protocol": "http",
							"host": [
								"localhost"
							],
							"port": "8080",
							"path": [
								"api",
								"detallesVenta",
								"agregarArticulo",
								"1"
							]
						}
					},
					"response": []
				}
			]
		},
		{
			"name": "Clientes",
			"item": [
				{
					"name": "Get All",
					"request": {
						"method": "GET",
						"header": [],
						"url": {
							"raw": "http://localhost:8080/api/clientes",
							"protocol": "http",
							"host": [
								"localhost"
							],
							"port": "8080",
							"path": [
								"api",
								"clientes"
							]
						}
					},
					"response": []
				},
				{
					"name": "Get One",
					"request": {
						"method": "GET",
						"header": [],
						"url": {
							"raw": "http://localhost:8080/api/articulos/1",
							"protocol": "http",
							"host": [
								"localhost"
							],
							"port": "8080",
							"path": [
								"api",
								"articulos",
								"1"
							]
						}
					},
					"response": []
				},
				{
					"name": "Create",
					"request": {
						"method": "POST",
						"header": [],
						"body": {
							"mode": "raw",
							"raw": "{\r\n    \"nombre\": \"Gerardo Guzmán\",\r\n    \"dni\": 12321\r\n    \r\n}",
							"options": {
								"raw": {
									"language": "json"
								}
							}
						},
						"url": {
							"raw": "http://localhost:8080/api/clientes",
							"protocol": "http",
							"host": [
								"localhost"
							],
							"port": "8080",
							"path": [
								"api",
								"clientes"
							]
						}
					},
					"response": []
				},
				{
					"name": "Update",
					"request": {
						"method": "PUT",
						"header": [],
						"body": {
							"mode": "raw",
							"raw": "{\r\n        \"id\": 4,\r\n        \"nombre\": \"Julio Guzmán\",\r\n        \"dni\": 3213242\r\n}",
							"options": {
								"raw": {
									"language": "json"
								}
							}
						},
						"url": {
							"raw": "http://localhost:8080/api/clientes/4",
							"protocol": "http",
							"host": [
								"localhost"
							],
							"port": "8080",
							"path": [
								"api",
								"clientes",
								"4"
							]
						}
					},
					"response": []
				},
				{
					"name": "Delete",
					"request": {
						"method": "DELETE",
						"header": [],
						"url": {
							"raw": "http://localhost:8080/api/clientes/2",
							"protocol": "http",
							"host": [
								"localhost"
							],
							"port": "8080",
							"path": [
								"api",
								"clientes",
								"2"
							]
						}
					},
					"response": []
				}
			]
		},
		{
			"name": "Proveedores",
			"item": [
				{
					"name": "Get All",
					"request": {
						"method": "GET",
						"header": [],
						"url": {
							"raw": "http://localhost:8080/api/proveedores",
							"protocol": "http",
							"host": [
								"localhost"
							],
							"port": "8080",
							"path": [
								"api",
								"proveedores"
							]
						}
					},
					"response": []
				},
				{
					"name": "Get One",
					"request": {
						"method": "GET",
						"header": [],
						"url": {
							"raw": "http://localhost:8080/api/proveedores/1",
							"protocol": "http",
							"host": [
								"localhost"
							],
							"port": "8080",
							"path": [
								"api",
								"proveedores",
								"1"
							]
						}
					},
					"response": []
				},
				{
					"name": "Create",
					"request": {
						"method": "POST",
						"header": [
							{
								"key": "Content-Type",
								"value": "application/json"
							}
						],
						"body": {
							"mode": "raw",
							"raw": "{   \r\n    \"nombre\":\"ale\",\r\n    \"telefono\":2613004548,\r\n    \"direccion\":\"Castelar 825\",\r\n    \"mail\":\"alear12373@gmail.com\",\r\n    \"fechaAlta\":\"2021-10-12T00:00:00\",\r\n    \"fechaBaja\":null\r\n}",
							"options": {
								"raw": {
									"language": "json"
								}
							}
						},
						"url": {
							"raw": "http://localhost:8080/api/proveedores",
							"protocol": "http",
							"host": [
								"localhost"
							],
							"port": "8080",
							"path": [
								"api",
								"proveedores"
							]
						}
					},
					"response": []
				},
				{
					"name": "Update",
					"request": {
						"method": "PUT",
						"header": [],
						"body": {
							"mode": "raw",
							"raw": "{\r\n    \"id\": 1,\r\n    \"nombreArticulo\": \"hamburguesa\",\r\n    \"detalle\": \"queso,tomate\",\r\n    \"fechaAlta\": \"2021-10-12T00:00:00.000+00:00\",\r\n    \"fechaBaja\": null,\r\n    \"loteOptimo\": 0,\r\n    \"puntoPedido\": 0,\r\n    \"stockSeguridad\": 0,\r\n    \"modelo\": null,\r\n    \"proveedorPredeterminado\": null,\r\n    \"cantActual\": 12,\r\n    \"cgi\": 0.0\r\n}",
							"options": {
								"raw": {
									"language": "json"
								}
							}
						},
						"url": {
							"raw": "http://localhost:8080/api/proveedores",
							"protocol": "http",
							"host": [
								"localhost"
							],
							"port": "8080",
							"path": [
								"api",
								"proveedores"
							]
						}
					},
					"response": []
				},
				{
					"name": "Delete",
					"request": {
						"method": "DELETE",
						"header": [],
						"url": {
							"raw": "http://localhost:8080/api/proveedores/1",
							"protocol": "http",
							"host": [
								"localhost"
							],
							"port": "8080",
							"path": [
								"api",
								"proveedores",
								"1"
							]
						}
					},
					"response": []
				}
			]
		},
		{
			"name": "ProveedorArticulos",
			"item": [
				{
					"name": "Get All",
					"request": {
						"method": "GET",
						"header": [],
						"url": {
							"raw": "http://localhost:8080/api/proveedores",
							"protocol": "http",
							"host": [
								"localhost"
							],
							"port": "8080",
							"path": [
								"api",
								"proveedores"
							]
						}
					},
					"response": []
				},
				{
					"name": "Get One",
					"request": {
						"method": "GET",
						"header": [],
						"url": {
							"raw": "http://localhost:8080/api/proveedores/1",
							"protocol": "http",
							"host": [
								"localhost"
							],
							"port": "8080",
							"path": [
								"api",
								"proveedores",
								"1"
							]
						}
					},
					"response": []
				},
				{
					"name": "Create",
					"request": {
						"method": "POST",
						"header": [
							{
								"key": "Content-Type",
								"value": "application/json"
							}
						],
						"body": {
							"mode": "raw",
							"raw": "{\r\n    \"fechaHoraBaja\":\"2021-10-12T00:00:00.000+00:00\",\r\n    \"fechaHoraAlta\":null,\r\n    \"tiempoPedido\":2,\r\n    \"costoPedido\":2.3,\r\n    \"costoAlmacenamiento\":null,\r\n    \"costoProducto\":33.2,\r\n    \"proveedor\":{\r\n    \"id\": 3,\r\n    \"nombre\": \"ale\",\r\n    \"telefono\": 2.613004548E9,\r\n    \"direccion\": \"Castelar 825\",\r\n    \"mail\": \"alear12373@gmail.com\",\r\n    \"fechaAlta\": \"2021-10-12T00:00:00.000+00:00\",\r\n    \"fechaBaja\": null\r\n},\r\n    \"articulo\":{\r\n    \"id\": 1,\r\n    \"nombreArticulo\": \"hamburguesa\",\r\n    \"detalle\": \"queso,tomate\",\r\n    \"fechaAlta\": \"2021-10-12T00:00:00.000+00:00\",\r\n    \"fechaBaja\": null,\r\n    \"loteOptimo\": 0,\r\n    \"puntoPedido\": 0,\r\n    \"stockSeguridad\": 0,\r\n    \"modelo\": \"MODELO_LOTE_FIJO\",\r\n    \"proveedorPredeterminado\": null,\r\n    \"cantActual\": 12,\r\n    \"cgi\": 0.0\r\n}\r\n}",
							"options": {
								"raw": {
									"language": "json"
								}
							}
						},
						"url": {
							"raw": "http://localhost:8080/api/proveedorArticulos",
							"protocol": "http",
							"host": [
								"localhost"
							],
							"port": "8080",
							"path": [
								"api",
								"proveedorArticulos"
							]
						}
					},
					"response": []
				},
				{
					"name": "Update",
					"request": {
						"method": "PUT",
						"header": [],
						"body": {
							"mode": "raw",
							"raw": "{\r\n    \"id\": 1,\r\n    \"nombreArticulo\": \"hamburguesa\",\r\n    \"detalle\": \"queso,tomate\",\r\n    \"fechaAlta\": \"2021-10-12T00:00:00.000+00:00\",\r\n    \"fechaBaja\": null,\r\n    \"loteOptimo\": 0,\r\n    \"puntoPedido\": 0,\r\n    \"stockSeguridad\": 0,\r\n    \"modelo\": null,\r\n    \"proveedorPredeterminado\": null,\r\n    \"cantActual\": 12,\r\n    \"cgi\": 0.0\r\n}",
							"options": {
								"raw": {
									"language": "json"
								}
							}
						},
						"url": {
							"raw": "http://localhost:8080/api/proveedores",
							"protocol": "http",
							"host": [
								"localhost"
							],
							"port": "8080",
							"path": [
								"api",
								"proveedores"
							]
						}
					},
					"response": []
				},
				{
					"name": "Delete",
					"request": {
						"method": "DELETE",
						"header": [],
						"url": {
							"raw": "http://localhost:8080/api/proveedores/1",
							"protocol": "http",
							"host": [
								"localhost"
							],
							"port": "8080",
							"path": [
								"api",
								"proveedores",
								"1"
							]
						}
					},
					"response": []
				}
			]
		},
		{
			"name": "Demanda",
			"item": [
				{
					"name": "Get All",
					"request": {
						"method": "GET",
						"header": [],
						"url": {
							"raw": "http://localhost:8080/api/demandas",
							"protocol": "http",
							"host": [
								"localhost"
							],
							"port": "8080",
							"path": [
								"api",
								"demandas"
							]
						}
					},
					"response": []
				},
				{
					"name": "Get One",
					"request": {
						"method": "GET",
						"header": [],
						"url": {
							"raw": "http://localhost:8080/api/demandas/1",
							"protocol": "http",
							"host": [
								"localhost"
							],
							"port": "8080",
							"path": [
								"api",
								"demandas",
								"1"
							]
						}
					},
					"response": []
				},
				{
					"name": "Create",
					"request": {
						"method": "POST",
						"header": [
							{
								"key": "Content-Type",
								"value": "application/json"
							}
						],
						"body": {
							"mode": "raw",
							"raw": "{   \r\n    \"nombre\":\"ale\",\r\n    \"telefono\":2613004548,\r\n    \"direccion\":\"Castelar 825\",\r\n    \"mail\":\"alear12373@gmail.com\",\r\n    \"fechaAlta\":\"2021-10-12T00:00:00\",\r\n    \"fechaBaja\":null\r\n}",
							"options": {
								"raw": {
									"language": "json"
								}
							}
						},
						"url": {
							"raw": "http://localhost:8080/api/demandas",
							"protocol": "http",
							"host": [
								"localhost"
							],
							"port": "8080",
							"path": [
								"api",
								"demandas"
							]
						}
					},
					"response": []
				},
				{
					"name": "Update",
					"request": {
						"method": "PUT",
						"header": [],
						"body": {
							"mode": "raw",
							"raw": "{\r\n    \"id\": 1,\r\n    \"nombreArticulo\": \"hamburguesa\",\r\n    \"detalle\": \"queso,tomate\",\r\n    \"fechaAlta\": \"2021-10-12T00:00:00.000+00:00\",\r\n    \"fechaBaja\": null,\r\n    \"loteOptimo\": 0,\r\n    \"puntoPedido\": 0,\r\n    \"stockSeguridad\": 0,\r\n    \"modelo\": null,\r\n    \"proveedorPredeterminado\": null,\r\n    \"cantActual\": 12,\r\n    \"cgi\": 0.0\r\n}",
							"options": {
								"raw": {
									"language": "json"
								}
							}
						},
						"url": {
							"raw": "http://localhost:8080/api/demandas",
							"protocol": "http",
							"host": [
								"localhost"
							],
							"port": "8080",
							"path": [
								"api",
								"demandas"
							]
						}
					},
					"response": []
				},
				{
					"name": "Delete",
					"request": {
						"method": "DELETE",
						"header": [],
						"url": {
							"raw": "http://localhost:8080/api/demandas/1",
							"protocol": "http",
							"host": [
								"localhost"
							],
							"port": "8080",
							"path": [
								"api",
								"demandas",
								"1"
							]
						}
					},
					"response": []
				}
			]
		}
	]
}